{
  "name": "The Galleon",
  "vendorId": "0x04D8",
  "productId": "0xEA2D",
  "matrix": {
    "rows": 14,
    "cols": 9
  },
  "lighting": "none",
  "layouts": {
    "labels": [
      "Split Backspace",
      "1U Plus",
      "1U Enter",
      "Bottom Row"
    ],
    "keymap": [
      [
        {
          "c": "#aaaaaa"
        },
        "0,0",
        {
          "x": 0.25
        },
        "1,0",
        "0,1",
        "1,1",
        "0,2",
        {
          "x": 0.25
        },
        "1,2",
        "0,3",
        "1,3",
        "0,4",
        {
          "x": 0.25
        },
        "1,4",
        "0,5",
        "1,5",
        "0,6",
        {
          "x": 1.75,
          "c": "#777777"
        },
        "0,7",
        "1,7",
        "0,8",
        "1,8"
      ],
      [
        "2,0",
        {
          "x": 0.25,
          "c": "#aaaaaa"
        },
        "3,0",
        "2,1",
        "3,1",
        "2,2",
        {
          "x": 0.25
        },
        "3,2",
        "2,3",
        "3,3",
        "2,4",
        {
          "x": 0.25
        },
        "3,4",
        "2,5",
        "3,5",
        "2,6",
        {
          "x": 1.75,
          "c": "#777777"
        },
        "2,7",
        "3,7",
        "2,8",
        "3,8"
      ],
      [
        {
          "y": -0.25,
          "x": 19.75,
          "c": "#aaaaaa"
        },
        "5,6\n\n\n0,1",
        "9,6\n\n\n0,1"
      ],
      [
        {
          "y": -0.5
        },
        "4,0",
        {
          "c": "#cccccc"
        },
        "5,0",
        "4,1",
        "5,1",
        "4,2",
        "5,2",
        "4,3",
        "5,3",
        "4,4",
        "5,4",
        "4,5",
        "5,5",
        "4,6",
        {
          "c": "#aaaaaa",
          "w": 2
        },
        "5,6\n\n\n0,0",
        {
          "x": 0.5
        },
        "4,7",
        "5,7",
        "4,8",
        "5,8"
      ],
      [
        {
          "w": 1.5
        },
        "6,0",
        {
          "c": "#cccccc"
        },
        "7,0",
        "6,1",
        "7,1",
        "6,2",
        "7,2",
        "6,3",
        "7,3",
        "6,4",
        "7,4",
        "6,5",
        "7,5",
        "6,6",
        {
          "c": "#aaaaaa",
          "w": 1.5
        },
        "7,6",
        {
          "x": 0.5
        },
        "6,7",
        "7,7",
        "6,8",
        {
          "c": "#777777",
          "h": 2
        },
        "7,8\n\n\n1,0",
        {
          "x": 0.25,
          "c": "#aaaaaa"
        },
        "7,8\n\n\n1,1"
      ],
      [
        {
          "w": 1.75
        },
        "8,0",
        {
          "c": "#cccccc"
        },
        "9,0",
        "8,1",
        "9,1",
        "8,2",
        "9,2",
        "8,3",
        "9,3",
        "8,4",
        "9,4",
        "8,5",
        "9,5",
        {
          "c": "#777777",
          "w": 2.25
        },
        "8,6",
        {
          "x": 0.5,
          "c": "#aaaaaa"
        },
        "8,7",
        "9,7",
        "8,8",
        {
          "x": 1.25
        },
        "9,8\n\n\n1,1"
      ],
      [
        {
          "w": 2.25
        },
        "10,0",
        {
          "c": "#cccccc"
        },
        "11,0",
        "10,1",
        "11,1",
        "10,2",
        "11,2",
        "10,3",
        "11,3",
        "10,4",
        "11,4",
        "10,5",
        {
          "c": "#aaaaaa",
          "w": 1.75
        },
        "10,6",
        {
          "x": 1.5
        },
        "10,7",
        "11,7",
        "10,8",
        {
          "c": "#777777",
          "h": 2
        },
        "11,8\n\n\n2,0",
        {
          "x": 0.25,
          "c": "#aaaaaa"
        },
        "11,8\n\n\n2,1"
      ],
      [
        {
          "y": -0.75,
          "x": 14.25,
          "c": "#777777"
        },
        "11,6"
      ],
      [
        {
          "y": -0.25,
          "c": "#aaaaaa",
          "w": 1.25
        },
        "12,0",
        {
          "w": 1.25
        },
        "13,0",
        {
          "w": 1.25
        },
        "12,1",
        {
          "w": 6.25
        },
        "12,2",
        {
          "w": 1.5
        },
        "12,4\n\n\n3,0",
        {
          "w": 1.5
        },
        "12,5\n\n\n3,0",
        {
          "x": 3.5
        },
        "13,7",
        "12,8",
        {
          "x": 1.25
        },
        "13,8\n\n\n2,1"
      ],
      [
        {
          "y": -0.75,
          "x": 13.25,
          "c": "#777777"
        },
        "12,6",
        "13,6",
        "12,7"
      ],
      [
        {
          "x": 10,
          "c": "#aaaaaa"
        },
        "12,4\n\n\n3,1",
        "13,4\n\n\n3,1",
        "12,5\n\n\n3,1"
      ]
    ]
  }
}
