{
  "name": "Flowerpad",
  "vendorId": "0x4D61",
  "productId": "0x466C",
  "matrix": {
    "rows": 3,
    "cols": 3
  },
  "layouts": {
    "keymap": [
      [
        {
          "rx": 0,
          "ry": 0,
          "y": -0.56,
          "x": 1
        },
        "0,1"
      ],
      [
        {
          "rx": -0.25,
          "ry": 0.6,
          "y": 0.6,
          "x": 1.25
        },
        "1,1"
      ],
      [
        {
          "r": 19.5,
          "rx": -0.44,
          "ry": 0.51
        },
        "1,0"
      ],
      [
        {
          "r": 36,
          "rx": 0.37,
          "ry": 2.44
        },
        "2,0"
      ],
      [
        {
          "r": -36,
          "rx": 1.83,
          "ry": 3
        },
        "2,2"
      ],
      [
        {
          "r": -19.5,
          "rx": 2.51,
          "ry": 0.84
        },
        "1,2"
      ]
    ]
  }
}
